dunebench/__init__.py
dunebench/__main__.py
dunebench-0.4.dist-info/METADATA
dunebench-0.4.dist-info/WHEEL
dunebench-0.4.dist-info/entry_points.txt
dunebench-0.4.dist-info/top_level.txt
dunebench-0.4.dist-info/RECORD
