Metadata-Version: 2.4
Name: dunebench
Version: 0.4
Summary: dunebench – a lightweight evaluation tool for llama.cpp models
Author: Rudransh Joshi
Author-email: rudranshseptmber@gmail.com
Classifier: Programming Language :: Python :: 3
Classifier: License :: OSI Approved :: MIT License
Classifier: Operating System :: OS Independent
Requires-Python: >=3.8
Requires-Dist: llama-cpp-python
Requires-Dist: datasets
Requires-Dist: tqdm
Dynamic: author
Dynamic: author-email
Dynamic: classifier
Dynamic: description
Dynamic: description-content-type
Dynamic: requires-dist
Dynamic: requires-python
Dynamic: summary
